yfinanceng/__init__.py
yfinanceng/base.py
yfinanceng/multi.py
yfinanceng/shared.py
yfinanceng/ticker.py
yfinanceng/tickers.py
yfinanceng/utils.py
yfinanceng-0.1.58.dist-info/LICENSE.txt
yfinanceng-0.1.58.dist-info/METADATA
yfinanceng-0.1.58.dist-info/WHEEL
yfinanceng-0.1.58.dist-info/entry_points.txt
yfinanceng-0.1.58.dist-info/top_level.txt
yfinanceng-0.1.58.dist-info/RECORD
