Metadata-Version: 2.1
Name: yfinanceng
Version: 0.1.58
Summary: Yahoo! Finance market data downloader
Home-page: https://github.com/larroy/yfinanceng
Author: Ran Aroussi
Author-email: pedro.larroy.lists@gmail.com
License: Apache
Keywords: pandas,yahoo finance,pandas datareader
Platform: any
Classifier: License :: OSI Approved :: Apache Software License
Classifier: Development Status :: 5 - Production/Stable
Classifier: Operating System :: OS Independent
Classifier: Intended Audience :: Developers
Classifier: Topic :: Office/Business :: Financial
Classifier: Topic :: Office/Business :: Financial :: Investment
Classifier: Topic :: Scientific/Engineering :: Interface Engine/Protocol Translator
Classifier: Topic :: Software Development :: Libraries
Classifier: Topic :: Software Development :: Libraries :: Python Modules
Classifier: Programming Language :: Python :: 3.4
Classifier: Programming Language :: Python :: 3.5
Classifier: Programming Language :: Python :: 3.6
Classifier: Programming Language :: Python :: 3.7
Requires-Python: >=3.6
License-File: LICENSE.txt
Requires-Dist: pandas (>=0.24)
Requires-Dist: numpy (>=1.15)
Requires-Dist: requests (>=2.20)
Requires-Dist: multitasking (>=0.0.7)
Requires-Dist: lxml
Requires-Dist: beautifulsoup4 (==4.9.0)
Requires-Dist: html5lib
Provides-Extra: test
Requires-Dist: tox ; extra == 'test'
Requires-Dist: flake8 ; extra == 'test'
Requires-Dist: black ; extra == 'test'
Requires-Dist: mock ; extra == 'test'
Requires-Dist: pre-commit ; extra == 'test'
Requires-Dist: nose ; extra == 'test'
Requires-Dist: pytest ; extra == 'test'
